ckanext/__init__.py
ckanext/workflow/__init__.py
ckanext/workflow/cli.py
ckanext/workflow/command.py
ckanext/workflow/helpers.py
ckanext/workflow/interface.py
ckanext/workflow/plugin.py
ckanext/workflow/states.py
ckanext/workflow/utils.py
ckanext/workflow/logic/__init__.py
ckanext/workflow/logic/action.py
ckanext/workflow/logic/auth.py
ckanext/workflow/tests/__init__.py
ckanext/workflow/tests/plugin.py
ckanext/workflow/tests/states.py
ckanext/workflow/tests/test_helpers.py
ckanext/workflow/tests/test_plugin.py
ckanext/workflow/tests/logic/__init__.py
ckanext/workflow/tests/logic/test_action.py
ckanext/workflow/tests/logic/test_auth.py
ckanext_workflow-2.0.0.dist-info/LICENSE
ckanext_workflow-2.0.0.dist-info/METADATA
ckanext_workflow-2.0.0.dist-info/WHEEL
ckanext_workflow-2.0.0.dist-info/entry_points.txt
ckanext_workflow-2.0.0.dist-info/top_level.txt
ckanext_workflow-2.0.0.dist-info/RECORD
