Metadata-Version: 2.1
Name: ckanext-workflow
Version: 2.0.0
Summary: Extended workflow for dataset lifecycle
Home-page: https://github.com/DataShades/ckanext-workflow
Author: Sergey Motornyuk
Author-email: sergey.motornyuk@linkdigital.com.au
License: AGPL
Keywords: CKAN ckanext workflow
Platform: UNKNOWN
Classifier: Development Status :: 4 - Beta
Classifier: License :: OSI Approved :: GNU Affero General Public License v3 or later (AGPLv3+)
Classifier: Programming Language :: Python :: 2.7
Classifier: Programming Language :: Python :: 3.5
Classifier: Programming Language :: Python :: 3.6
Classifier: Programming Language :: Python :: 3.7
Requires-Dist: ckantoolkit
Requires-Dist: six
